[
    {
        "id": 1554252125332455425,
        "full_text": "RT @Cinthia21704470: Bolsonaro. Inquérito q se refere a acusação contra Bolsonaro, sob alegação de q ele publicou na íntegra um inquérito d…",
        "created_at": "2022-08-01 23:45:57",
        "source": "Twitter for Android",
        "retweet_count": 4
    },
    {
        "id": 1554252124325908481,
        "full_text": "RT @ducavendish: Globo colocando macacos na tela ao falar de racismo contra crianças e humorista da esquerda caviar agredindo apoiadores do…",
        "created_at": "2022-08-01 23:45:57",
        "source": "Twitter for Android",
        "retweet_count": 78
    },
    {
        "id": 1554252123881316354,
        "full_text": "RT @JornalBSM: A PGR já havia pedido arquivmento do inquérito que investiga se Bolsonaro cometeu crime por divulgar relatório da PF sobre a…",
        "created_at": "2022-08-01 23:45:57",
        "source": "Twitter for iPhone",
        "retweet_count": 2
    },
    {
        "id": 1554252123881209856,
        "full_text": "RT @Zivaniacandu: A senhora( 70 anos) da lanchonete disse: \"você viu q o homem fez agora? Baixou mais imposto, gasolina não para d baixar,t…",
        "created_at": "2022-08-01 23:45:57",
        "source": "Twitter for Android",
        "retweet_count": 497
    },
    {
        "id": 1554252123633754112,
        "full_text": "RT @JornalBSM: A PGR já havia pedido arquivmento do inquérito que investiga se Bolsonaro cometeu crime por divulgar relatório da PF sobre a…",
        "created_at": "2022-08-01 23:45:57",
        "source": "Twitter for Android",
        "retweet_count": 2
    },
    {
        "id": 1554252123138834433,
        "full_text": "RT @lazarorosa25: Esse é o empresário bolsonarista que bateu e cuspiu no rosto de uma professora que se manifestou contra o Bolsonaro em Te…",
        "created_at": "2022-08-01 23:45:57",
        "source": "Twitter for Android",
        "retweet_count": 232
    },
    {
        "id": 1554252122367168524,
        "full_text": "RT @Fa1ryNight: O podcast é sobre a fraude da Teoria de gênero e de repente aparece o homi no meio da conversa.\n\nBolsonaro como pai \nBolson…",
        "created_at": "2022-08-01 23:45:57",
        "source": "Twitter for Android",
        "retweet_count": 1535
    },
    {
        "id": 1554252121981304832,
        "full_text": "RT @Biakicis: A Subprocuradora-Geral da República, Lindôra Araújo, diz que Alexandre de Moraes violou o sistema acusatório em inquérito con…",
        "created_at": "2022-08-01 23:45:57",
        "source": "Twitter Web App",
        "retweet_count": 626
    },
    {
        "id": 1554252120290893827,
        "full_text": "RT @senadorhumberto: A política armamentista de Bolsonaro está dando munição ao crime no Brasil. https://t.co/Ju4EUGTghN",
        "created_at": "2022-08-01 23:45:56",
        "source": "Twitter for Android",
        "retweet_count": 171
    },
    {
        "id": 1554252119913422862,
        "full_text": "RT @ChegaLogo2023: Faltam 153 Dias para o fim do desgoverno Bolsonaro",
        "created_at": "2022-08-01 23:45:56",
        "source": "Twitter for Android",
        "retweet_count": 1
    },
    {
        "id": 1554252119645081600,
        "full_text": "RT @JovemPanNews: Bolsonaro (PL) mostra força no eleitorado de São Paulo\n\n#3em1 | Por Constantino: “O Paraná Pesquisas é um instituto que t…",
        "created_at": "2022-08-01 23:45:56",
        "source": "Twitter for Android",
        "retweet_count": 86
    },
    {
        "id": 1554252119632486401,
        "full_text": "RT @bellexcosta: Presidente Rodolfo Landim veio junto com a delegação do #Flamengo para a partida contra o Corinthians. Dorival Júnior como…",
        "created_at": "2022-08-01 23:45:56",
        "source": "Twitter for iPhone",
        "retweet_count": 40
    },
    {
        "id": 1554252119087136768,
        "full_text": "RT @saulchristos: Tudo isso na mesma Fortaleza onde há poucos dias Bolsonaro arrastou uma multidão numa motociata noturna!\n\nVem pra rua, Lu…",
        "created_at": "2022-08-01 23:45:56",
        "source": "Twitter for Android",
        "retweet_count": 1190
    },
    {
        "id": 1554252119066173442,
        "full_text": "RT @marcofeliciano: Segundo a Paraná Pesquisas, o instituto que mais acertou em 2018 e 2022, Presidente Bolsonaro abriu 4 pontos em São Pau…",
        "created_at": "2022-08-01 23:45:56",
        "source": "Twitter for iPhone",
        "retweet_count": 603
    },
    {
        "id": 1554252118789443585,
        "full_text": "RT @brom_elisa: 💰Enquanto a 4ª Economia do mundo registra queda de 8,8% nas vendas no Varejo em Junho, o Brasil,10ª Economia Mundial cresce…",
        "created_at": "2022-08-01 23:45:56",
        "source": "Twitter for Android",
        "retweet_count": 688
    },
    {
        "id": 1554252117115797504,
        "full_text": "Colocar em dúvida resultado da eleição é defender 'interesse próprio', diz Fachin | Eleições 2022 | G1 https://t.co/6ND0wyBuQZ",
        "created_at": "2022-08-01 23:45:55",
        "source": "Twitter for Android",
        "retweet_count": 0
    },
    {
        "id": 1554252117048795138,
        "full_text": "RT @Brasinha1: A @PaolaCarosella já voltou para Argentina?\nOu está no Brasil colhendo os frutos do governo Bolsonaro a quem ela criticou? h…",
        "created_at": "2022-08-01 23:45:55",
        "source": "Twitter for Android",
        "retweet_count": 331
    },
    {
        "id": 1554252117027819520,
        "full_text": "Uma abençoada noite excelência...\n\nAonde está o presidente do Senado Federal??? https://t.co/YuOT95tMDe",
        "created_at": "2022-08-01 23:45:55",
        "source": "Twitter for Android",
        "retweet_count": 0
    },
    {
        "id": 1554252116960608257,
        "full_text": "RT @BolsonaroSP: Para a Financial Times disse “eu não acredito nas pesquisas”.\n\nMesmo que muitas pesquisas digam que Lula e Bolsonaro estej…",
        "created_at": "2022-08-01 23:45:55",
        "source": "Twitter for iPhone",
        "retweet_count": 706
    },
    {
        "id": 1554252116335656960,
        "full_text": "22/8 Jornal Nacional entrevista Bolsonaro. Que tal tirar as panelas da cozinha para fazer barulho… #panelaço",
        "created_at": "2022-08-01 23:45:55",
        "source": "Twitter for iPhone",
        "retweet_count": 0
    },
    {
        "id": 1554252115136155649,
        "full_text": "URGENTE BOLSONARO MOBILIZA NAÇÃO LULA TEM MAIS UMA DERROTA PETISTA DÁ SI... https://t.co/hxk7hAwpO2 via @YouTube",
        "created_at": "2022-08-01 23:45:55",
        "source": "Twitter Web App",
        "retweet_count": 0
    },
    {
        "id": 1554252114947215362,
        "full_text": "CORNOS COM BOLSONARO https://t.co/69sQLSLPDb",
        "created_at": "2022-08-01 23:45:55",
        "source": "Twitter for Android",
        "retweet_count": 0
    },
    {
        "id": 1554252112925757447,
        "full_text": "Essa semana eu já me mudo   home :)",
        "created_at": "2022-08-01 23:45:54",
        "source": "Twitter for Android",
        "retweet_count": 0
    },
    {
        "id": 1554252111675785216,
        "full_text": "@TerraBrasilnot Quer dizer que transparência nas eleições é interesse próprio? Só se for interesse próprio do país!",
        "created_at": "2022-08-01 23:45:54",
        "source": "Twitter for Android",
        "retweet_count": 0
    },
    {
        "id": 1554252111654928384,
        "full_text": "RT @BolsonaroSP: Para a Financial Times disse “eu não acredito nas pesquisas”.\n\nMesmo que muitas pesquisas digam que Lula e Bolsonaro estej…",
        "created_at": "2022-08-01 23:45:54",
        "source": "Twitter for Android",
        "retweet_count": 706
    },
    {
        "id": 1554252110937706499,
        "full_text": "RT @Antagoniza11: Veja o poder de compra  do antigo Bolsa Família do PT e do Auxílio Brasil de Bolsonaro.\n@joaoromaneto @jairbolsonaro \n@Ca…",
        "created_at": "2022-08-01 23:45:54",
        "source": "Twitter for Android",
        "retweet_count": 3
    },
    {
        "id": 1554252110757257216,
        "full_text": "RT @desmentindobozo: \"Falta de aptidão pra ser presidente\"\n\"Um desastre absoluto na pandemia\"\n\nEste é o senador Fernando Collor, aliado do…",
        "created_at": "2022-08-01 23:45:54",
        "source": "Twitter for Android",
        "retweet_count": 1833
    },
    {
        "id": 1554252109977210881,
        "full_text": "RT @kimpaim: Michelle Bolsonaro tá sendo criticada pela GLOBO por levar evangélicos para orar de noite no Planalto?\n\nPor que odeiam tanto o…",
        "created_at": "2022-08-01 23:45:54",
        "source": "Twitter for Android",
        "retweet_count": 1830
    },
    {
        "id": 1554252108983148544,
        "full_text": "fumo maconha e apoio o bolsonaro",
        "created_at": "2022-08-01 23:45:54",
        "source": "Twitter for Android",
        "retweet_count": 0
    },
    {
        "id": 1554252107351576576,
        "full_text": "RT @tarcisiogdf: Olha só o Brasil mostrando resiliência. O mercado esperava deflação de -0,76% no IPC-S. Os mais otimistas esperavam -1,12%…",
        "created_at": "2022-08-01 23:45:53",
        "source": "Twitter for Android",
        "retweet_count": 627
    },
    {
        "id": 1554252107288649730,
        "full_text": "Todo mundo já sabe:\nBOLSONARO NÃO TRABALHA https://t.co/l6NsXJ4Ti2",
        "created_at": "2022-08-01 23:45:53",
        "source": "Twitter Web App",
        "retweet_count": 0
    },
    {
        "id": 1554252106609164294,
        "full_text": "RT @reporterenato: Presidente Jair Bolsonaro atende ultimato do ministro Kássio Nunes, do STF, e indica Messod Azulay Neto e Paulo Sérgio D…",
        "created_at": "2022-08-01 23:45:53",
        "source": "Twitter for Android",
        "retweet_count": 414
    },
    {
        "id": 1554252106168958976,
        "full_text": "RT @TerraBrasilnot: URGENTE: Nova pesquisa mostra Bolsonaro disparado à frente de Lula https://t.co/oeO52PDo60",
        "created_at": "2022-08-01 23:45:53",
        "source": "Twitter for Android",
        "retweet_count": 615
    },
    {
        "id": 1554252105824849923,
        "full_text": "RT @saulchristos: \"Ain, não voto em Bolsonaro por causa do Roberto Jefferson, do Waldemar e do Cunha\".\n\nÉ mesmo, isentão?\n\nA real: Se já pa…",
        "created_at": "2022-08-01 23:45:53",
        "source": "Twitter for Android",
        "retweet_count": 1067
    },
    {
        "id": 1554252105652883461,
        "full_text": "RT @CarlaZambelli38: PGR volta a pedir que o STF arquive o inquérito que apura se o presidente @JairBolsonaro vazou dados sigilosos de uma…",
        "created_at": "2022-08-01 23:45:53",
        "source": "Twitter for Android",
        "retweet_count": 189
    },
    {
        "id": 1554252104784658432,
        "full_text": "RT @Biakicis: A Subprocuradora-Geral da República, Lindôra Araújo, diz que Alexandre de Moraes violou o sistema acusatório em inquérito con…",
        "created_at": "2022-08-01 23:45:53",
        "source": "Twitter for Android",
        "retweet_count": 626
    },
    {
        "id": 1554252104176484354,
        "full_text": "@L_JiangJade Muito obrigada❤ eu fico feliz em ler isso❤❤\n\nEsses dias eu tenho estado meio :( como a minha escrita😕",
        "created_at": "2022-08-01 23:45:52",
        "source": "Twitter for Android",
        "retweet_count": 0
    },
    {
        "id": 1554252104000208898,
        "full_text": "RT @CarolDeToni: LULA É O CANDIDATO DA INTERNACIONALIZAÇÃO DA AMAZÔNIA. BOLSONARO É O PATRIOTA QUE ESTÁ NO CAMINHO LUTANDO CONTRA ISSO. htt…",
        "created_at": "2022-08-01 23:45:52",
        "source": "Twitter for iPhone",
        "retweet_count": 273
    },
    {
        "id": 1554252103757041664,
        "full_text": "RT @a_postagem: Por que os grandes capitalistas estão abandonando Bolsonaro? https://t.co/jZikE80202",
        "created_at": "2022-08-01 23:45:52",
        "source": "Twitter Web App",
        "retweet_count": 4
    },
    {
        "id": 1554252102440034305,
        "full_text": "@RoLuchsinger Casa com um presidente, minha filha! 🤣🤣🤣🤣🤣🤣🤣🤣🤣🤣🤣",
        "created_at": "2022-08-01 23:45:52",
        "source": "Twitter for Android",
        "retweet_count": 0
    },
    {
        "id": 1554252101877891072,
        "full_text": "RT @CrapulaLeonardo: Esse Tablet ainda funciona com Java e 2G. Só tomando socada do Presidente. 🤣🤣🤣 https://t.co/ugePAo4Lyk",
        "created_at": "2022-08-01 23:45:52",
        "source": "Twitter for Android",
        "retweet_count": 112
    },
    {
        "id": 1554252101420711936,
        "full_text": "@Ejohnyss num dá :(",
        "created_at": "2022-08-01 23:45:52",
        "source": "Twitter for Android",
        "retweet_count": 0
    },
    {
        "id": 1554252100330217474,
        "full_text": "RT @CrapulaLeonardo: Esse Tablet ainda funciona com Java e 2G. Só tomando socada do Presidente. 🤣🤣🤣 https://t.co/ugePAo4Lyk",
        "created_at": "2022-08-01 23:45:51",
        "source": "Twitter for Android",
        "retweet_count": 112
    },
    {
        "id": 1554252100279963654,
        "full_text": "mais um mês sem ver meus amores :( https://t.co/k2chSm5YZU",
        "created_at": "2022-08-01 23:45:51",
        "source": "Twitter for Android",
        "retweet_count": 0
    },
    {
        "id": 1554252098660868098,
        "full_text": "RT @AnaAlic18810883: #RodrigoGarciaNunca\n@rodrigogarcia_  O grande inimigo dos Aposentados GovSP. Confisca, suga, massacra os Aposentados.…",
        "created_at": "2022-08-01 23:45:51",
        "source": "Twitter Web App",
        "retweet_count": 11
    },
    {
        "id": 1554252098535047168,
        "full_text": "@jairbolsonaro @madruga2022 Não sabia quem era esse maracatu, mas a faca do presidente foi afiada , mito é mito. 👏🏻👏🏻👏🏻👏🏻👏🏻 #capitaodopovo",
        "created_at": "2022-08-01 23:45:51",
        "source": "Twitter for iPhone",
        "retweet_count": 0
    },
    {
        "id": 1554252097742405637,
        "full_text": "RT @Cinthia21704470: PÉ DE GUERRA.... Há duas semanas que a PGR está entrando de sola em Alexandre de Moraes. Moraes tem violado processos…",
        "created_at": "2022-08-01 23:45:51",
        "source": "Twitter for iPhone",
        "retweet_count": 7
    },
    {
        "id": 1554252097675198466,
        "full_text": "RT @biazitagomes: Bolsonaro tem de 25% à 30% de um eleitorado fiel.\nA base do Bolsonarismo é o ultra conservadorismo e como consequência um…",
        "created_at": "2022-08-01 23:45:51",
        "source": "Twitter for Android",
        "retweet_count": 14
    },
    {
        "id": 1554252097666834432,
        "full_text": "to mal, fico muito mal quando vejo gente falando mal de su, esse desenho é muito importante pra mim, é meu conforto :(",
        "created_at": "2022-08-01 23:45:51",
        "source": "Twitter for iPhone",
        "retweet_count": 0
    },
    {
        "id": 1554252097105051648,
        "full_text": "@iIychim @Iittlemaknae eu dedicaria cada letra das músicas mais bonitas existentes pra ele, lulu :( ele é o maior amor da minha vida, meu único coração",
        "created_at": "2022-08-01 23:45:51",
        "source": "Twitter for iPhone",
        "retweet_count": 0
    },
    {
        "id": 1554252096236560384,
        "full_text": "CORNOS COM BOLSONARO\no candidato dos cornos\nsó corno vota em bozonaro\no mito dos cornos https://t.co/FvQS09c7YN",
        "created_at": "2022-08-01 23:45:51",
        "source": "Twitter for iPhone",
        "retweet_count": 0
    },
    {
        "id": 1554252096224075779,
        "full_text": "RT @realpfigueiredo: Acreditem se quiserem: em pleno governo Bolsonaro, estão tentando transformar o Palácio da antiga residência da Famíli…",
        "created_at": "2022-08-01 23:45:51",
        "source": "Twitter for iPhone",
        "retweet_count": 1887
    },
    {
        "id": 1554252095884337152,
        "full_text": "*Saiba quem são os dois indicados por Jair Bolsonaro para o STJ*\n\nMessod Azulay Neto e Paulo Sérgio Domingues passarão agora por avaliação do Senado Federal\n\nhttps://t.co/7OVsNovwj0",
        "created_at": "2022-08-01 23:45:50",
        "source": "Twitter for Android",
        "retweet_count": 0
    },
    {
        "id": 1554252095741693952,
        "full_text": "RT @tesoureiros: Passou 4 anos andando de moto e jetski enquanto a gente se lascava de trabalhar pra sustentar as mordomias dele\n\nBOLSONARO…",
        "created_at": "2022-08-01 23:45:50",
        "source": "Twitter for iPhone",
        "retweet_count": 1016
    },
    {
        "id": 1554252095225749511,
        "full_text": "RT @Biakicis: A Subprocuradora-Geral da República, Lindôra Araújo, diz que Alexandre de Moraes violou o sistema acusatório em inquérito con…",
        "created_at": "2022-08-01 23:45:50",
        "source": "Twitter Web App",
        "retweet_count": 626
    },
    {
        "id": 1554252094806396929,
        "full_text": "@josepaulorosam1 Vou ser redundante meu amigo. \nNovamente você foi cirúrgico.\nEla eleição não será sobre Eleger Presidente,  Governador,  Senador,  Deputado Federal e Estadual.\nÉ sobre sua liberdade.  A nossa Soberania, sua própria e as riquezas do Brasil.  \nVote corretamente, por favor",
        "created_at": "2022-08-01 23:45:50",
        "source": "Twitter for Android",
        "retweet_count": 0
    },
    {
        "id": 1554252094772846594,
        "full_text": "RT @Robert_jus: Quer dizer que o dono das lojas  @Lojas_Renner assinou cartinha contra o Presidente @jairbolsonaro ? Acabei de cancelar meu…",
        "created_at": "2022-08-01 23:45:50",
        "source": "Twitter for Android",
        "retweet_count": 726
    },
    {
        "id": 1554252094500212737,
        "full_text": "RT @FlavioBolsonaro: Desemprego em queda, PIB em alta, preço dos combustíveis caindo, exportações crescendo…\n\nÉ o Brasil que dá certo com B…",
        "created_at": "2022-08-01 23:45:50",
        "source": "Twitter for Android",
        "retweet_count": 580
    },
    {
        "id": 1554252094080786435,
        "full_text": "RT @Conservadora191: CANDIDATOS DO PTB não poderão aparecer na foto com o presidente @jairbolsonaro , pois o candidato do partido é o Rober…",
        "created_at": "2022-08-01 23:45:50",
        "source": "Twitter Web App",
        "retweet_count": 4
    },
    {
        "id": 1554252093808074752,
        "full_text": "RT @PedroRonchi2: Como as fakes sobre Cuba e Venezuela não colam mais, os bolsonaristas estão desesperados falando da Argentina. Só que tam…",
        "created_at": "2022-08-01 23:45:50",
        "source": "Twitter for Android",
        "retweet_count": 174
    },
    {
        "id": 1554252093568974848,
        "full_text": "RT @FabioClickTime: Quando pretendem usar uma nova bandeira, é preciso cancelar a atual.\nO cancelamento da nossa bandeira, não é apenas por…",
        "created_at": "2022-08-01 23:45:50",
        "source": "Twitter for Android",
        "retweet_count": 17
    },
    {
        "id": 1554252093078249472,
        "full_text": "RT @Zivaniacandu: No ônibus,minha frente tem 2jovens(22+ou-) Passamos frente posto d gasolina e 1comenta:\n\"-Sabia gasolina mais barato do m…",
        "created_at": "2022-08-01 23:45:50",
        "source": "Twitter for Android",
        "retweet_count": 752
    },
    {
        "id": 1554252092545564677,
        "full_text": "RT @CarolDeToni: Pois eis que, agora, o Paraná Pesquisas publica levantamento que coloca Bolsonaro a frente no maior colégio eleitoral do p…",
        "created_at": "2022-08-01 23:45:50",
        "source": "Twitter for Android",
        "retweet_count": 92
    },
    {
        "id": 1554252092344340482,
        "full_text": "RT @SandraMorenah22: A esquerda já não se sustenta mais. Esgotaram-se as narrativas, acabou a munição. O desespero bateu e as evidências sã…",
        "created_at": "2022-08-01 23:45:50",
        "source": "Twitter for Android",
        "retweet_count": 372
    },
    {
        "id": 1554252092222722053,
        "full_text": "RT @desmentindobozo: \"Falta de aptidão pra ser presidente\"\n\"Um desastre absoluto na pandemia\"\n\nEste é o senador Fernando Collor, aliado do…",
        "created_at": "2022-08-01 23:45:50",
        "source": "Twitter Web App",
        "retweet_count": 1833
    },
    {
        "id": 1554252090511425536,
        "full_text": "TSE e PGE vão enfrentar violência contra a mulher nas eleições. Veja mais em:  - https://t.co/rC3QkDu6C0",
        "created_at": "2022-08-01 23:45:49",
        "source": "tribunadosertao",
        "retweet_count": 0
    },
    {
        "id": 1554252090364551170,
        "full_text": "RT @reporterenato: Em discurso no STF, o ministro Luiz Fux pediu que candidatos e eleitores sejam leais à Constituição e respeitem a manife…",
        "created_at": "2022-08-01 23:45:49",
        "source": "Twitter for Android",
        "retweet_count": 18
    },
    {
        "id": 1554252090133909504,
        "full_text": "RT @senadorhumberto: BOLSONARO NÃO TRABALHA. E ele mesmo já admitiu isso 👇 https://t.co/g7JrM0iiay",
        "created_at": "2022-08-01 23:45:49",
        "source": "Twitter Web App",
        "retweet_count": 255
    },
    {
        "id": 1554252089265643520,
        "full_text": "@Matheus16499946 Salve, Matheus! Aguarde o final da rodada para que os lances sejam revisados e a pontuação seja computada em definitivo. Peço que leve em consideração os critérios utilizados e acompanhe as notícias da rodada para ficar por dentro de tudo que rola. Qualquer dúvida é só chamar! :)",
        "created_at": "2022-08-01 23:45:49",
        "source": "Buzzmonitor ",
        "retweet_count": 0
    },
    {
        "id": 1554252088615616514,
        "full_text": "RT @revistaoeste: Simone Tebet confirma vice feminina sem citar senadora Mara Gabrilli https://t.co/Y6YNyk1JQj",
        "created_at": "2022-08-01 23:45:49",
        "source": "Twitter for Android",
        "retweet_count": 4
    },
    {
        "id": 1554252088305139712,
        "full_text": "RT @CentralEleicoes: 📺 JORNAL NACIONAL: Um sorteio definiu a ordem das entrevistas com os candidatos à presidência no Jornal Nacional. \n\nA…",
        "created_at": "2022-08-01 23:45:49",
        "source": "Twitter for Android",
        "retweet_count": 151
    },
    {
        "id": 1554252087676076035,
        "full_text": "@fyodorfobic fofo :( te amo lili",
        "created_at": "2022-08-01 23:45:48",
        "source": "Twitter for iPhone",
        "retweet_count": 0
    },
    {
        "id": 1554252087659270149,
        "full_text": "RT @ultradireita191: O maior adversário,do Bolsonaro. https://t.co/McYyNxKbHu",
        "created_at": "2022-08-01 23:45:48",
        "source": "Twitter for Android",
        "retweet_count": 19
    },
    {
        "id": 1554252087181148162,
        "full_text": "RT @doucegw: vejo as pessoas ao meu redor comendo pãо de quеijo, сооkie, bolacha etc. de manhã e fico pensando em como deve ser bom nao ter…",
        "created_at": "2022-08-01 23:45:48",
        "source": "Twitter for Android",
        "retweet_count": 17
    },
    {
        "id": 1554252086677835776,
        "full_text": "RT @GuilhermeBoulos: ABSURDO! Empresário bolsonarista bateu e cuspiu em rosto de mulher que gritava \"Fora, Bolsonaro\" no RJ. A violência é…",
        "created_at": "2022-08-01 23:45:48",
        "source": "Twitter for Android",
        "retweet_count": 493
    },
    {
        "id": 1554252086136676352,
        "full_text": "RT @fpassos1964: Por favor, não escrevam em caixa alta CORNOS COM BOLSONARO. Nem pensem em dar RT comentando CORNOS COM BOLSONARO. O Carlux…",
        "created_at": "2022-08-01 23:45:48",
        "source": "Twitter for iPhone",
        "retweet_count": 56
    },
    {
        "id": 1554252085872529408,
        "full_text": "RT @CrapulaLeonardo: Esse Tablet ainda funciona com Java e 2G. Só tomando socada do Presidente. 🤣🤣🤣 https://t.co/ugePAo4Lyk",
        "created_at": "2022-08-01 23:45:48",
        "source": "Twitter for Android",
        "retweet_count": 112
    },
    {
        "id": 1554252085792751627,
        "full_text": "RT @FlavioBolsonaro: Desemprego em queda, PIB em alta, preço dos combustíveis caindo, exportações crescendo…\n\nÉ o Brasil que dá certo com B…",
        "created_at": "2022-08-01 23:45:48",
        "source": "Twitter for Android",
        "retweet_count": 580
    },
    {
        "id": 1554252085721501697,
        "full_text": "@LulaOficial @ricardostuckert O Brasil feliz de novo, meu presidente @LulaOficial 🇧🇷1️⃣3️⃣🚩",
        "created_at": "2022-08-01 23:45:48",
        "source": "Twitter for Android",
        "retweet_count": 0
    },
    {
        "id": 1554252084769427457,
        "full_text": "RT @VEJA: Nova pesquisa mostra Bolsonaro à frente de Lula em São Paulo &gt;&gt;&gt; https://t.co/R8JZQtCWK7 https://t.co/uG1Xt9Kg2f",
        "created_at": "2022-08-01 23:45:48",
        "source": "Twitter for Android",
        "retweet_count": 431
    },
    {
        "id": 1554252084727496704,
        "full_text": "RT @LinsBel03: @BrazilFight Que \"democracia\" os amigos de Lowla defendem para que Bolsonaro assine o tal Manifesto? 🤡",
        "created_at": "2022-08-01 23:45:48",
        "source": "Twitter Web App",
        "retweet_count": 1
    },
    {
        "id": 1554252084341514241,
        "full_text": "RT @eumesmavivi0: Começou os saques na Argentina...\n\nO presidente apoiado pelo Lula, destruiu o país...\n\n#BolsonaroReeleitoEm2022 https://t…",
        "created_at": "2022-08-01 23:45:48",
        "source": "Twitter for Android",
        "retweet_count": 1414
    },
    {
        "id": 1554252084144488449,
        "full_text": "RT @artevillar1: BOLSONARO NÃO TRABALHA https://t.co/4HL4iRSI7j",
        "created_at": "2022-08-01 23:45:48",
        "source": "Twitter for Android",
        "retweet_count": 566
    },
    {
        "id": 1554252083670425602,
        "full_text": "@Mar_Pinho1 @cirogomes Nao, pra Paris. E antes das eleições.",
        "created_at": "2022-08-01 23:45:48",
        "source": "Twitter Web App",
        "retweet_count": 0
    },
    {
        "id": 1554252083502653445,
        "full_text": "RT @Cinthia21704470: IMBATÍVEL..... O presidente alcançou 22 milhões de seguidores no Insta. Se somarmos aos 19 milhões no Face + 8,5 milhõ…",
        "created_at": "2022-08-01 23:45:47",
        "source": "Twitter for iPad",
        "retweet_count": 55
    },
    {
        "id": 1554252082861019136,
        "full_text": "RT @VEJA: Nova pesquisa mostra Bolsonaro à frente de Lula em São Paulo &gt;&gt;&gt; https://t.co/R8JZQtCWK7 https://t.co/uG1Xt9Kg2f",
        "created_at": "2022-08-01 23:45:47",
        "source": "Twitter for iPhone",
        "retweet_count": 431
    },
    {
        "id": 1554252082705752065,
        "full_text": "RT @CarlaZambelli38: PGR volta a pedir que o STF arquive o inquérito que apura se o presidente @JairBolsonaro vazou dados sigilosos de uma…",
        "created_at": "2022-08-01 23:45:47",
        "source": "Twitter for Android",
        "retweet_count": 188
    },
    {
        "id": 1554252082454183938,
        "full_text": "RT @RoLuchsinger: Michele Bolsonaro precisa entender que o Estado é laico e que o palácio não é igreja.",
        "created_at": "2022-08-01 23:45:47",
        "source": "Twitter for Android",
        "retweet_count": 223
    },
    {
        "id": 1554252082005348354,
        "full_text": "RT @PastorSamoel: Quando as crianças gostam é porque é verdadeiro, Bolsonaro reeleito já 🇧🇷 https://t.co/46GeaHVJ4I",
        "created_at": "2022-08-01 23:45:47",
        "source": "Twitter Web App",
        "retweet_count": 52
    },
    {
        "id": 1554252081636286466,
        "full_text": "RT @reinaldoazevedo: Então Kássio com K ameaçou romper “parceria” com Bolsonaro caso contrariado em indicações para o STJ? É isso mesmo? O…",
        "created_at": "2022-08-01 23:45:47",
        "source": "Twitter for iPhone",
        "retweet_count": 757
    },
    {
        "id": 1554252081594343426,
        "full_text": "RT @IrlanSimoes: Infelizmente foi confirmada a morte de Mauro Machado Urbim, presidente da Fúria Independente do Paraná Clube, após ser pis…",
        "created_at": "2022-08-01 23:45:47",
        "source": "Twitter for Android",
        "retweet_count": 255
    },
    {
        "id": 1554252081325920257,
        "full_text": "@theluvsuk KKKKKKK sério?? eu tb, yoongi n quer vir morar cmgo :(",
        "created_at": "2022-08-01 23:45:47",
        "source": "Twitter for Android",
        "retweet_count": 0
    },
    {
        "id": 1554252081325817862,
        "full_text": "RT @lazarorosa25: Esse é o empresário bolsonarista que bateu e cuspiu no rosto de uma professora que se manifestou contra o Bolsonaro em Te…",
        "created_at": "2022-08-01 23:45:47",
        "source": "Twitter Web App",
        "retweet_count": 232
    },
    {
        "id": 1554252080910684160,
        "full_text": "@VirniusPrincess pqp, sinto muito katha :(",
        "created_at": "2022-08-01 23:45:47",
        "source": "Twitter for iPhone",
        "retweet_count": 0
    },
    {
        "id": 1554252080851947523,
        "full_text": "RT @BrazilFight: KIM D. PAIM\n\"Mentir sobre Bolsonaro é fácil, que ver é a imprensa falar a verdade sobre o Lula.\"",
        "created_at": "2022-08-01 23:45:47",
        "source": "Twitter for Android",
        "retweet_count": 886
    },
    {
        "id": 1554252080075898880,
        "full_text": "OBRAS DO GOVERNO BOLSONARO...COMEÇO, MEIO E FIM...INVESTIMENTO, SOMENTE DENTRO DO BRASIL. https://t.co/Zb3Yw6V1f5",
        "created_at": "2022-08-01 23:45:47",
        "source": "Twitter for Android",
        "retweet_count": 0
    },
    {
        "id": 1554252079652282368,
        "full_text": "RT @kimpaim: Michelle Bolsonaro tá sendo criticada pela GLOBO por levar evangélicos para orar de noite no Planalto?\n\nPor que odeiam tanto o…",
        "created_at": "2022-08-01 23:45:47",
        "source": "Twitter for Android",
        "retweet_count": 1830
    },
    {
        "id": 1554252076976427013,
        "full_text": "@requiaooficial Faltam 61 dias pra votar no Lula presidente pela terceira vez. Requião governador de novo.",
        "created_at": "2022-08-01 23:45:46",
        "source": "Twitter for Android",
        "retweet_count": 0
    },
    {
        "id": 1554252076938674179,
        "full_text": "@VanderleiANune5 Você é o TIPO de gado dos mais desprezíveis, já defendeu Moro, já defendeu o Bolsonaro nas mortes em Manaus, já defendeu política de preços da Petrobras, compartilha Bia Kicis Alexandre Garcia.\nLamentável\nVc nem pra Gado serve, tamanha falta de qualidade",
        "created_at": "2022-08-01 23:45:46",
        "source": "Twitter for Android",
        "retweet_count": 0
    },
    {
        "id": 1554252074619215877,
        "full_text": "fiquei mal com isso da série da harley, sabe não tinha necessidade de quererem piada com esse assunto :(",
        "created_at": "2022-08-01 23:45:45",
        "source": "Twitter Web App",
        "retweet_count": 0
    }
]